README.rst
setup.cfg
setup.py
transposer/__init__.py
transposer/transposer.py
transposer.egg-info/PKG-INFO
transposer.egg-info/SOURCES.txt
transposer.egg-info/dependency_links.txt
transposer.egg-info/entry_points.txt
transposer.egg-info/top_level.txt
transposer/script/__init__.py
transposer/script/console_script.py