Metadata-Version: 1.1
Name: transposer
Version: 0.0.3
Summary: Transposes columns and rows in delimited text files
Home-page: https://github.com/keithhamilton/transposer
Author: Keith Hamilton
Author-email: the.keith.hamilton@gmail.com
License: BSD License
Keywords: text,csv,tab-delimited,delimited,excel,sheet,spreadsheet
Platform: UNKNOWN
Classifier: Development Status :: 4 - Beta
Classifier: Intended Audience :: Developers
Classifier: License :: OSI Approved :: MIT License
Classifier: Programming Language :: Python
Classifier: Programming Language :: Python :: 2.6
Classifier: Programming Language :: Python :: 2.7
Classifier: Topic :: Office/Business
